__init__.py
qmath.py
quaternions.py
quaternions_for_python_zachartrand-1.1.2.dist-info/LICENSE.md
quaternions_for_python_zachartrand-1.1.2.dist-info/METADATA
quaternions_for_python_zachartrand-1.1.2.dist-info/WHEEL
quaternions_for_python_zachartrand-1.1.2.dist-info/top_level.txt
quaternions_for_python_zachartrand-1.1.2.dist-info/RECORD
