Metadata-Version: 2.1
Name: quaternions-for-python-zachartrand
Version: 1.1.2
Summary: A module for using quaternions in Python.
Author-email: Zach Chartrand <zachartrand999@gmail.com>
License: # MIT License        
Project-URL: Homepage, https://github.com/zachartrand/Quaternions
Project-URL: Bug Tracker, https://github.com/zachartrand/Quaternions/issues
Keywords: quaternion,rotation,rotate,3d,euler,spin,complex,imaginary,dot,cross,product,gimbal-lock,hamilton,versor,norm,vector,axis,math,mathematics
Classifier: Programming Language :: Python :: 3
Classifier: License :: OSI Approved :: MIT License
Classifier: Operating System :: OS Independent
Requires-Python: >=3.8
License-File: LICENSE.md
